phanos/__init__.py
phanos/config.py
phanos/log.py
phanos/messaging.py
phanos/metrics.py
phanos/publisher.py
phanos/py.typed
phanos/tree.py
phanos/types.py
phanos-0.3.2.dist-info/METADATA
phanos-0.3.2.dist-info/WHEEL
phanos-0.3.2.dist-info/licenses/LICENSE
phanos-0.3.2.dist-info/RECORD
