Metadata-Version: 2.3
Name: phanos
Version: 0.3.2
Summary: Python client to gather data for Prometheus logging in server with multiple instances and workers.
Project-URL: Homepage, https://github.com/kajotgames/phanos
Project-URL: Bug Tracker, https://github.com/kajotgames/phanos/issues
Author-email: Miroslav Bulička <bulickamiroslav@gmail.com>
License-File: LICENSE
Classifier: Intended Audience :: Developers
Classifier: Intended Audience :: System Administrators
Classifier: License :: OSI Approved :: MIT License
Classifier: Operating System :: OS Independent
Classifier: Programming Language :: Python
Classifier: Programming Language :: Python :: 3
Classifier: Topic :: System :: Monitoring
Requires-Python: >=3.10.6
Requires-Dist: aio-pika>=9.2
Requires-Dist: orjson>=3.9
Requires-Dist: pika>=1.3.2
Requires-Dist: pip>=23.1.2
